altdns/__init__.py
altdns/__main__.py
py_altdns-1.0.0.dist-info/LICENSE
py_altdns-1.0.0.dist-info/METADATA
py_altdns-1.0.0.dist-info/WHEEL
py_altdns-1.0.0.dist-info/entry_points.txt
py_altdns-1.0.0.dist-info/top_level.txt
py_altdns-1.0.0.dist-info/RECORD
