Metadata-Version: 2.1
Name: py-altdns
Version: 1.0.0
Summary: Generates permutations, alterations and mutations of subdomains and then resolves them.
Home-page: https://github.com/infosec-au/altdns
Author: Shubham Shah
Author-email: sshah@assetnote.io
License: UNKNOWN
Platform: UNKNOWN
Classifier: Programming Language :: Python :: 2.7
Classifier: License :: OSI Approved :: Apache Software License
Classifier: Operating System :: OS Independent
Classifier: Topic :: Security
Requires-Dist: tldextract
Requires-Dist: argparse
Requires-Dist: termcolor
Requires-Dist: dnspython
